{
  "name": "Mindful Garden Walk",
  "name_fr": "Promenade M횄짤ditative au Jardin",
  "category": "nature",
  "icon": "챨혺혣쨘",
  "description": "A mindful walk through Pamplemousses botanical garden with meditation stops, guided by @bea_titudeyoga.",
  "description_fr": "Une promenade m횄짤ditative 횄혻 travers le jardin botanique de Pamplemousses avec des pauses m횄짤ditation, guid횄짤e par @bea_titudeyoga.",
  "duration": "2 hours",
  "duration_fr": "2 heures",
  "price": 30,
  "unit": "person",
  "instagram": "https://www.instagram.com/bea_titudeyoga/",
  "photo": "/images/Hero.jpg",
  "gallery": [
    "/images/Hero.jpg"
  ],
  "active": false
}